{
  "basics": {
    "name": "Nicholas (Kiko) Whiteley",
    "label": "Student",
    "picture": "https://github.com/keekss.png",
    "email": "new2@hawaii.edu",
    "phone": "808-741-1881",
    "website": "https://keekss.github.io",
    "summary": "I am studying Computer Science and Mathematics at the University of Hawaii at Manoa with an emphasis on machine learning.  I also work part-time as a technician for Apple Retail.",
    "location": {
      "address": "",
      "postalCode": "96825",
      "city": "Honolulu",
      "countryCode": "USA",
      "region": "Hawaii" 
    },
    "profiles": [
      {
        "network": "github", 
        "username": "keekss", 
        "url": "http://github.com/keekss" 
      },
      { 
        "network": "linkedin", 
        "username": "kiko-whiteley", 
        "url": "https://www.linkedin.com/in/kiko-whiteley/" 
      }
    ]
  },
  "interests": [
    { "name": "Machine Learning" },
    { "name": "Network Science" },
    { "name": "Big Data Analytics" },
    { "name": "Software Engineering" }
  ],
  "skills": [
    {
      "name": "Languages",
      "keywords": [ "Python", "R", "Javascript", "C++" ]
    },
    {
      "name": "Frameworks",
      "keywords": [ "Apache Spark", "Dash" ]
    }
  ],
  "education": [
    {
      "institution": "University of Hawaii at Manoa, Honolulu, HI",
      "area": "Computer Science, Mathematics",
      "studyType": "B.S.",
      "startDate": "2020",
      "endDate": "Present",
      "courses": [
      ]
    },
    {
      "institution": "Southern Methodist University, Dallas, TX",
      "area": "General Business",
      "studyType": "B.B.A",
      "startDate": "2013-08-24",
      "endDate": "2018-05-20",
      "gpa": "",
      "courses": []
    }
  ],
  "work": [
    {
      "company": "Apple, Inc.",
      "position": "Technical Specialist",
      "website": "",
      "startDate": "2021-11",
      "endDate": "Present",
      "summary": "",
      "highlights": [
        "Perform and arrange hardware repairs as well as software troubleshooting for in-store customers"
      ]
    },
    {
      "company": "Apple, Inc.",
      "position": "Specialist",
      "website": "",
      "startDate": "2019-06",
      "endDate": "2021-11",
      "summary": "",
      "highlights": [
        "Advised in-store customers on purchases, troubleshooting, and setup of Apple and related products"
      ]
    },
    {
      "company": "WR Sales",
      "position": "Water Sporting Goods Distributor",
      "website": "",
      "startDate": "2018-07",
      "endDate": "2020-01",
      "summary": "",
      "highlights": [
        "Fulfilled orders for ten retail stores on Oahu, Maui, Kauai, and Hawaii island",
        "Stocked, organized, and tracked warehouse inventory"
      ]
    },
    {
      "company": "Greenhill Cogent (f.k.a. Cogent Partners)",
      "position": "Private Equity Intern",
      "website": "",
      "startDate": "2015-08",
      "endDate": "2018-05",
      "summary": "",
      "highlights": [
        "Automated conditional data retrieval and aggregation from closed Excel workbooks using Excel Visual Basic programming",
        "Authored a firm-wide fund naming convention to streamline analysis of historical data"
      ]
    }
  ],
  "volunteer": [
    {
      "organization": "Tunes for Texas",
      "website": "",
      "position": "Event Organizer and Performer",
      "startDate": "2013-09-01",
      "endDate": "2018-05-20",
      "summary": "",
      "highlights": [
        "Organized and performed music in four annual university clothing drives as well as Christmas caroling and music teaching events at Dallas elementary and middle schools"
      ]
    }
  ],
  "references": [
    {
      "name": "Available upon request",
      "reference": ""
    }
  ]
}
